dromo/__init__.py
dromo-0.1.0.dist-info/WHEEL
dromo-0.1.0.dist-info/METADATA
dromo-0.1.0.dist-info/RECORD
